LICENSE
README.md
pyproject.toml
setup.py
search_view_pkg_Anurag09.egg-info/PKG-INFO
search_view_pkg_Anurag09.egg-info/SOURCES.txt
search_view_pkg_Anurag09.egg-info/dependency_links.txt
search_view_pkg_Anurag09.egg-info/top_level.txt
src/__init__.py
src/search_products.py