Metadata-Version: 2.1
Name: search-view-pkg-Anurag09
Version: 0.0.1
Summary: A package to search products in the RoundLab APP
Home-page: https://github.com/Annurag99/RoundLab
Author: Anurag Singh
Author-email: 
License: UNKNOWN
Platform: UNKNOWN
License-File: LICENSE
